drf_events/__init__.py
drf_events/event_handlers/__init__.py
drf_events/event_handlers/aws.py
drf_events/event_handlers/log.py
drf_events/exceptions.py
drf_events/mixins.py
drf_events-0.1.1a7.dist-info/METADATA
drf_events-0.1.1a7.dist-info/WHEEL
drf_events-0.1.1a7.dist-info/RECORD
